datatransfer/__init__.py
datatransfer/version.conf
datatransfer/common/__init__.py
datatransfer/common/configuration.py
datatransfer/common/constants.py
datatransfer/common/helpers.py
datatransfer/common/messages.py
datatransfer/common/smev256.py
datatransfer/common/mapping/__init__.py
datatransfer/common/mapping/enum.py
datatransfer/common/utils/__init__.py
datatransfer/common/utils/test.py
datatransfer/common/xml/__init__.py
datatransfer/common/xml/parser.py
datatransfer/source/__init__.py
datatransfer/source/actions.py
datatransfer/source/app_meta.py
datatransfer/source/configs.py
datatransfer/source/permissions.py
datatransfer/source/plugin_meta.py
datatransfer/source/tasks.py
datatransfer/source/ui.py
datatransfer/source/utils.py
datatransfer/source/catalog/__init__.py
datatransfer/source/catalog/actions.py
datatransfer/source/catalog/app_meta.py
datatransfer/source/catalog/apps.py
datatransfer/source/catalog/exceptions.py
datatransfer/source/catalog/model_views.py
datatransfer/source/catalog/models.py
datatransfer/source/catalog/permissions.py
datatransfer/source/catalog/plugin_meta.py
datatransfer/source/catalog/tasks.py
datatransfer/source/catalog/ui.py
datatransfer/source/catalog/utils.py
datatransfer/source/catalog/migrations/0001_initial.py
datatransfer/source/catalog/migrations/0002_feedback_comment_update_charfield_to_textfield.py
datatransfer/source/catalog/migrations/__init__.py
datatransfer/source/catalog/project_models/__init__.py
datatransfer/source/catalog/project_models/common.py
datatransfer/source/catalog/report/__init__.py
datatransfer/source/catalog/report/builder.py
datatransfer/source/catalog/report/provider.py
datatransfer/source/catalog/report/report.py
datatransfer/source/catalog/report/report.xls
datatransfer/source/catalog/report/report.xlsx
datatransfer/source/catalog/south_migrations/0001_initial.py
datatransfer/source/catalog/south_migrations/0002_feedback_comment_update_charfield_to_textfield.py
datatransfer_client-2.13.0.dist-info/METADATA
datatransfer_client-2.13.0.dist-info/WHEEL
datatransfer_client-2.13.0.dist-info/dependency_links.txt
datatransfer_client-2.13.0.dist-info/top_level.txt
datatransfer_client-2.13.0.dist-info/RECORD
