Metadata-Version: 2.4
Name: datatransfer_client
Version: 2.13.0
Author: BARS Group
Classifier: Intended Audience :: Developers
Classifier: Environment :: Web Environment
Classifier: Natural Language :: Russian
Classifier: Programming Language :: Python
Classifier: Programming Language :: Python :: 3.7
Classifier: Development Status :: 5 - Production/Stable
Classifier: Framework :: Django :: 1.11
Classifier: Framework :: Django :: 2.0
Classifier: Framework :: Django :: 2.1
Classifier: Framework :: Django :: 2.2
Classifier: Framework :: Django :: 3.0
Classifier: Framework :: Django :: 3.1
Classifier: Framework :: Django :: 3.2
Classifier: Framework :: Django :: 4.0
Classifier: Framework :: Django :: 4.1
Requires-Dist: lxml<4.7,>=4.5
Requires-Dist: petl<1.3,>=1.2
Requires-Dist: yadic==0.1.12.6
Requires-Dist: m3-builder<2,>=1.2
Requires-Dist: m3-django-compatibility<2,>=1.12.0
Dynamic: author
Dynamic: classifier
Dynamic: requires-dist
